ply/__init__.py
ply/lex.py
ply/yacc.py
plyara/__init__.py
plyara/command_line.py
plyara/core.py
plyara/exceptions.py
plyara/utils.py
plyara-2.2.7.dist-info/LICENSE
plyara-2.2.7.dist-info/METADATA
plyara-2.2.7.dist-info/WHEEL
plyara-2.2.7.dist-info/entry_points.txt
plyara-2.2.7.dist-info/top_level.txt
plyara-2.2.7.dist-info/RECORD
